mlonmcu/__init__.py
mlonmcu/artifact.py
mlonmcu/config.py
mlonmcu/logging.py
mlonmcu/mlonmcu.py
mlonmcu/plugins.py
mlonmcu/report.py
mlonmcu/timeout.py
mlonmcu/utils.py
mlonmcu/version.py
mlonmcu/cli/__init__.py
mlonmcu/cli/build.py
mlonmcu/cli/cleanup.py
mlonmcu/cli/common.py
mlonmcu/cli/compile.py
mlonmcu/cli/env.py
mlonmcu/cli/export.py
mlonmcu/cli/flow.py
mlonmcu/cli/init.py
mlonmcu/cli/load.py
mlonmcu/cli/main.py
mlonmcu/cli/models.py
mlonmcu/cli/run.py
mlonmcu/cli/setup.py
mlonmcu/cli/tune.py
mlonmcu/cli/helper/__init__.py
mlonmcu/cli/helper/filter.py
mlonmcu/cli/helper/parse.py
mlonmcu/context/__init__.py
mlonmcu/context/context.py
mlonmcu/context/read_write_filelock.py
mlonmcu/environment/__init__.py
mlonmcu/environment/config.py
mlonmcu/environment/environment.py
mlonmcu/environment/init.py
mlonmcu/environment/list.py
mlonmcu/environment/loader.py
mlonmcu/environment/templates.py
mlonmcu/environment/writer.py
mlonmcu/feature/__init__.py
mlonmcu/feature/feature.py
mlonmcu/feature/features.py
mlonmcu/feature/type.py
mlonmcu/flow/__init__.py
mlonmcu/flow/backend.py
mlonmcu/flow/framework.py
mlonmcu/flow/tflm/__init__.py
mlonmcu/flow/tflm/framework.py
mlonmcu/flow/tflm/backend/__init__.py
mlonmcu/flow/tflm/backend/backend.py
mlonmcu/flow/tflm/backend/tflmc.py
mlonmcu/flow/tflm/backend/tflmi.py
mlonmcu/flow/tvm/__init__.py
mlonmcu/flow/tvm/framework.py
mlonmcu/flow/tvm/backend/__init__.py
mlonmcu/flow/tvm/backend/backend.py
mlonmcu/flow/tvm/backend/model_info.py
mlonmcu/flow/tvm/backend/python_utils.py
mlonmcu/flow/tvm/backend/tuner.py
mlonmcu/flow/tvm/backend/tvmaot.py
mlonmcu/flow/tvm/backend/tvmaotplus.py
mlonmcu/flow/tvm/backend/tvmc_utils.py
mlonmcu/flow/tvm/backend/tvmcg.py
mlonmcu/flow/tvm/backend/tvmllvm.py
mlonmcu/flow/tvm/backend/tvmrt.py
mlonmcu/flow/tvm/backend/wrapper.py
mlonmcu/models/__init__.py
mlonmcu/models/convert_data.py
mlonmcu/models/frontend.py
mlonmcu/models/group.py
mlonmcu/models/lookup.py
mlonmcu/models/metadata.py
mlonmcu-0.7.0.dist-info/LICENSE
mlonmcu-0.7.0.dist-info/METADATA
mlonmcu-0.7.0.dist-info/NOTICE
mlonmcu-0.7.0.dist-info/WHEEL
mlonmcu-0.7.0.dist-info/entry_points.txt
mlonmcu-0.7.0.dist-info/top_level.txt
mlonmcu-0.7.0.dist-info/RECORD
