Metadata-Version: 2.1
Name: mlonmcu
Version: 0.7.0
Summary: This project contains research code related to the deployment of inferenceor learning applications on tiny micro-controllers.
Home-page: https://github.com/tum-ei-eda/mlonmcu
Author: TUM Department of Electrical and Computer Engineering - Chair of Electronic Design Automation
Author-email: philipp.van-kempen@tum.de
License: Apache License 2.0
Keywords: mlonmcu
Platform: UNKNOWN
Classifier: Development Status :: 2 - Pre-Alpha
Classifier: Intended Audience :: Developers
Classifier: License :: OSI Approved :: Apache Software License
Classifier: Natural Language :: English
Classifier: Programming Language :: Python :: 3
Classifier: Programming Language :: Python :: 3.6
Classifier: Programming Language :: Python :: 3.7
Classifier: Programming Language :: Python :: 3.8
Classifier: Programming Language :: Python :: 3.9
Classifier: Programming Language :: Python :: 3.10
Classifier: Programming Language :: Python :: 3.11
Requires-Python: >=3.7
License-File: LICENSE
License-File: NOTICE
Requires-Dist: GitPython
Requires-Dist: Pillow
Requires-Dist: filelock
Requires-Dist: humanize
Requires-Dist: jinja2 (>=3.1.3)
Requires-Dist: networkx
Requires-Dist: numpy (<2.0)
Requires-Dist: openpyxl
Requires-Dist: pandas
Requires-Dist: paramiko
Requires-Dist: pyelftools
Requires-Dist: pyyaml
Requires-Dist: tqdm
Requires-Dist: xdg
Requires-Dist: xlsxwriter
Requires-Dist: xlwt
Provides-Extra: all-prod
Requires-Dist: GitPython ; extra == 'all-prod'
Requires-Dist: Pillow ; extra == 'all-prod'
Requires-Dist: PrettyTable ; extra == 'all-prod'
Requires-Dist: anytree ; extra == 'all-prod'
Requires-Dist: attrs ; extra == 'all-prod'
Requires-Dist: bitstring (>=3.1.6) ; extra == 'all-prod'
Requires-Dist: click (>=7.0) ; extra == 'all-prod'
Requires-Dist: cloudpickle ; extra == 'all-prod'
Requires-Dist: construct (==2.10.54) ; extra == 'all-prod'
Requires-Dist: cryptography (>=2.1.4) ; extra == 'all-prod'
Requires-Dist: decorator ; extra == 'all-prod'
Requires-Dist: ecdsa (>=0.16.0) ; extra == 'all-prod'
Requires-Dist: filelock ; extra == 'all-prod'
Requires-Dist: future (>=0.15.2) ; extra == 'all-prod'
Requires-Dist: gdbgui (==0.13.2.0) ; extra == 'all-prod'
Requires-Dist: graphviz ; extra == 'all-prod'
Requires-Dist: humanize ; extra == 'all-prod'
Requires-Dist: hydra-core ; extra == 'all-prod'
Requires-Dist: idf-component-manager (~=1.0) ; extra == 'all-prod'
Requires-Dist: itsdangerous (<2.1) ; extra == 'all-prod'
Requires-Dist: jinja2 (>=3.1.3) ; extra == 'all-prod'
Requires-Dist: kconfiglib (==13.7.1) ; extra == 'all-prod'
Requires-Dist: matplotlib ; extra == 'all-prod'
Requires-Dist: networkx ; extra == 'all-prod'
Requires-Dist: numpy (<2.0) ; extra == 'all-prod'
Requires-Dist: onnx ; extra == 'all-prod'
Requires-Dist: openpyxl ; extra == 'all-prod'
Requires-Dist: ortools ; extra == 'all-prod'
Requires-Dist: pandas ; extra == 'all-prod'
Requires-Dist: paramiko ; extra == 'all-prod'
Requires-Dist: psutil ; extra == 'all-prod'
Requires-Dist: pyelftools ; extra == 'all-prod'
Requires-Dist: pygdbmi (<=0.9.0.2) ; extra == 'all-prod'
Requires-Dist: pyparsing (<2.4.0,>=2.0.3) ; extra == 'all-prod'
Requires-Dist: pyserial ; extra == 'all-prod'
Requires-Dist: python-socketio (<5) ; extra == 'all-prod'
Requires-Dist: pyusb ; extra == 'all-prod'
Requires-Dist: pyyaml ; extra == 'all-prod'
Requires-Dist: reedsolo (<=1.5.4,>=1.5.3) ; extra == 'all-prod'
Requires-Dist: relayviz ; extra == 'all-prod'
Requires-Dist: scipy ; extra == 'all-prod'
Requires-Dist: synr ; extra == 'all-prod'
Requires-Dist: tensorflow (~=2.13.0) ; extra == 'all-prod'
Requires-Dist: tflite (>=2.4.0) ; extra == 'all-prod'
Requires-Dist: tornado ; extra == 'all-prod'
Requires-Dist: tqdm ; extra == 'all-prod'
Requires-Dist: typing-extensions ; extra == 'all-prod'
Requires-Dist: xdg ; extra == 'all-prod'
Requires-Dist: xgboost (>=1.7.0) ; extra == 'all-prod'
Requires-Dist: xlsxwriter ; extra == 'all-prod'
Requires-Dist: xlwt ; extra == 'all-prod'
Provides-Extra: espidf
Requires-Dist: bitstring (>=3.1.6) ; extra == 'espidf'
Requires-Dist: click (>=7.0) ; extra == 'espidf'
Requires-Dist: construct (==2.10.54) ; extra == 'espidf'
Requires-Dist: cryptography (>=2.1.4) ; extra == 'espidf'
Requires-Dist: ecdsa (>=0.16.0) ; extra == 'espidf'
Requires-Dist: future (>=0.15.2) ; extra == 'espidf'
Requires-Dist: gdbgui (==0.13.2.0) ; extra == 'espidf'
Requires-Dist: idf-component-manager (~=1.0) ; extra == 'espidf'
Requires-Dist: itsdangerous (<2.1) ; extra == 'espidf'
Requires-Dist: jinja2 (>=3.1.3) ; extra == 'espidf'
Requires-Dist: kconfiglib (==13.7.1) ; extra == 'espidf'
Requires-Dist: psutil ; extra == 'espidf'
Requires-Dist: pygdbmi (<=0.9.0.2) ; extra == 'espidf'
Requires-Dist: pyparsing (<2.4.0,>=2.0.3) ; extra == 'espidf'
Requires-Dist: pyserial ; extra == 'espidf'
Requires-Dist: python-socketio (<5) ; extra == 'espidf'
Requires-Dist: reedsolo (<=1.5.4,>=1.5.3) ; extra == 'espidf'
Provides-Extra: etiss
Requires-Dist: humanize ; extra == 'etiss'
Requires-Dist: pyelftools ; extra == 'etiss'
Provides-Extra: gvsoc_pulp
Requires-Dist: PrettyTable ; extra == 'gvsoc_pulp'
Provides-Extra: microtvm
Requires-Dist: matplotlib ; extra == 'microtvm'
Requires-Dist: pyserial ; extra == 'microtvm'
Requires-Dist: pyusb ; extra == 'microtvm'
Provides-Extra: microtvm_gvsoc
Requires-Dist: hydra-core ; extra == 'microtvm_gvsoc'
Provides-Extra: moiopt
Requires-Dist: ortools ; extra == 'moiopt'
Provides-Extra: onnx
Requires-Dist: onnx ; extra == 'onnx'
Provides-Extra: relay-visualization
Requires-Dist: relayviz ; extra == 'relay-visualization'
Provides-Extra: tflite
Requires-Dist: tflite (>=2.4.0) ; extra == 'tflite'
Provides-Extra: tflm
Requires-Dist: Pillow ; extra == 'tflm'
Provides-Extra: tvm
Requires-Dist: anytree ; extra == 'tvm'
Requires-Dist: attrs ; extra == 'tvm'
Requires-Dist: cloudpickle ; extra == 'tvm'
Requires-Dist: decorator ; extra == 'tvm'
Requires-Dist: graphviz ; extra == 'tvm'
Requires-Dist: matplotlib ; extra == 'tvm'
Requires-Dist: numpy (<2.0) ; extra == 'tvm'
Requires-Dist: psutil ; extra == 'tvm'
Requires-Dist: scipy ; extra == 'tvm'
Requires-Dist: synr ; extra == 'tvm'
Requires-Dist: tornado ; extra == 'tvm'
Requires-Dist: typing-extensions ; extra == 'tvm'
Provides-Extra: tvm-autotuning
Requires-Dist: xgboost (>=1.7.0) ; extra == 'tvm-autotuning'
Provides-Extra: visualize
Requires-Dist: matplotlib ; extra == 'visualize'
Provides-Extra: visualize_tflite
Requires-Dist: tensorflow (~=2.13.0) ; extra == 'visualize_tflite'
Provides-Extra: zephyr
Requires-Dist: pyserial ; extra == 'zephyr'
